{"Controlador.Lista.ListaSimple":{"cabecera":{"dato":{"@class":"Modelo.Cuenta","id":1,"usuario":"cris","clave":1234},"sig":{"dato":{"@class":"Modelo.Cuenta","id":1,"usuario":"cris","clave":1234},"sig":{"dato":{"@class":"Modelo.Cuenta","id":1,"usuario":"cris","clave":1234},"sig":{"dato":{"@class":"Modelo.Cuenta","id":1,"usuario":"cris","clave":1234},"sig":{"dato":{"@class":"Modelo.Cuenta","id":1,"usuario":"cris","clave":1234},"sig":{"dato":{"@class":"Modelo.Cuenta","id":1,"usuario":"cris","clave":1234},"sig":{"dato":{"@class":"Modelo.Cuenta","id":1,"usuario":"cris","clave":1234},"sig":{"dato":{"@class":"Modelo.Cuenta","id":1,"usuario":"cris","clave":1234},"sig":{"dato":{"@class":"Modelo.Cuenta","id":1,"usuario":"cris","clave":1234},"sig":{"dato":{"@class":"Modelo.Cuenta","id":1,"usuario":"cris","clave":1234},"sig":{"dato":{"@class":"Modelo.Cuenta","id":1,"usuario":"cris","clave":1234},"sig":{"dato":{"@class":"Modelo.Cuenta","id":1,"usuario":"cris","clave":1234},"sig":{"dato":{"@class":"Modelo.Cuenta","id":1,"usuario":"cris","clave":1234},"sig":{"dato":{"@class":"Modelo.Cuenta","id":1,"usuario":"cris","clave":1234},"sig":{"dato":{"@class":"Modelo.Cuenta","id":1,"usuario":"cris","clave":1234},"sig":{"dato":{"@class":"Modelo.Cuenta","id":1,"usuario":"cris","clave":1234},"sig":{"dato":{"@class":"Modelo.Cuenta","id":1,"usuario":"cris","clave":1234},"sig":{"dato":{"@class":"Modelo.Cuenta","id":1,"usuario":"cris","clave":1234},"sig":{"dato":{"@class":"Modelo.Cuenta","id":1,"usuario":"cris","clave":1234},"sig":{"dato":{"@class":"Modelo.Cuenta","id":1,"usuario":"cris","clave":1234},"sig":{"dato":{"@class":"Modelo.Cuenta","id":1,"usuario":"cris","clave":1234},"sig":{"dato":{"@class":"Modelo.Cuenta","id":1,"usuario":"cris","clave":1234},"sig":{"dato":{"@class":"Modelo.Cuenta","id":1,"usuario":"cris","clave":1234},"sig":{"dato":{"@class":"Modelo.Cuenta","id":1,"usuario":"cris","clave":1234}}}}}}}}}}}}}}}}}}}}}}}}}}}